cursofiap/__init__.py
cursofiap/core.py
curso_fiap-1.0.0.dist-info/METADATA
curso_fiap-1.0.0.dist-info/WHEEL
curso_fiap-1.0.0.dist-info/top_level.txt
curso_fiap-1.0.0.dist-info/RECORD
